embcompare/__init__.py
embcompare/_version.py
embcompare/cli.py
embcompare/config.py
embcompare/embedding.py
embcompare/embeddings_compare.py
embcompare/export_utils.py
embcompare/load_utils.py
embcompare/reports.py
embcompare/sequences_similarity.py
embcompare/gui/__init__.py
embcompare/gui/app.py
embcompare/gui/helpers.py
embcompare/gui/features/__init__.py
embcompare/gui/features/config_comparison.py
embcompare/gui/features/frequencies_comparison.py
embcompare/gui/features/global_param_selection.py
embcompare/gui/features/neighborhoods_comparison.py
embcompare/gui/features/neighborhoods_sim_stats.py
embcompare/gui/features/space_comparison.py
embcompare/gui/features/statistics_comparison.py
embcompare-1.0.1.dist-info/LICENSE
embcompare-1.0.1.dist-info/METADATA
embcompare-1.0.1.dist-info/WHEEL
embcompare-1.0.1.dist-info/entry_points.txt
embcompare-1.0.1.dist-info/top_level.txt
embcompare-1.0.1.dist-info/RECORD
