Metadata-Version: 2.1
Name: embcompare
Version: 1.0.1
Summary: EmbCompare is a small python package that helps you compare your embeddings both visually and numerically.
Author-email: Agence Data Services PE Nantes <contactadsaiframeworks.00619@pole-emploi.fr>
License: GNU AFFERO GENERAL PUBLIC LICENSE
Project-URL: homepage, https://github.com/OSS-Pole-Emploi/emcompare
Project-URL: documentation, https://github.com/OSS-Pole-Emploi/emcompare
Project-URL: repository, https://github.com/OSS-Pole-Emploi/emcompare
Project-URL: Bug Tracker, https://github.com/OSS-Pole-Emploi/emcompare/issues
Classifier: Natural Language :: English
Classifier: Operating System :: OS Independent
Classifier: Programming Language :: Python
Classifier: Programming Language :: Python :: 3.8
Classifier: Programming Language :: Python :: 3.9
Classifier: Programming Language :: Python :: 3.10
Classifier: Topic :: Scientific/Engineering :: Artificial Intelligence
Classifier: Topic :: Scientific/Engineering :: Information Analysis
Classifier: Topic :: Software Development :: User Interfaces
Classifier: License :: OSI Approved :: GNU Affero General Public License v3
Requires-Python: <4.0,>=3.8
License-File: LICENSE
Requires-Dist: gensim (<5.0,>=4.0)
Requires-Dist: scikit-learn (<1.3,>=1.1)
Requires-Dist: numpy (<2.0,>=1.19)
Requires-Dist: omegaconf (<3.0,>=2.0)
Requires-Dist: click (<9.0,>=8.0)
Provides-Extra: dev
Requires-Dist: black (>=19.0) ; extra == 'dev'
Requires-Dist: isort (>=4.3) ; extra == 'dev'
Requires-Dist: pytest (<8.0,>=7.0) ; extra == 'dev'
Requires-Dist: pytest-cov (<5.0,>=3.0) ; extra == 'dev'
Requires-Dist: pytest-datadir (<2.0,>=1.0) ; extra == 'dev'
Requires-Dist: nox (>=2022) ; extra == 'dev'
Provides-Extra: gui
Requires-Dist: streamlit (<2,>=1.12) ; extra == 'gui'
Requires-Dist: pandas (<2.0,>=1.3) ; extra == 'gui'
Requires-Dist: altair (<5.0,>=4.0) ; extra == 'gui'
Requires-Dist: loguru (<1.0,>=0.6) ; extra == 'gui'
Provides-Extra: test
Requires-Dist: pytest (<8.0,>=7.0) ; extra == 'test'
Requires-Dist: pytest-cov (<5.0,>=3.0) ; extra == 'test'
Requires-Dist: pytest-datadir (<2.0,>=1.0) ; extra == 'test'
